ee_ampere_consultoria/__init__.py
ee_ampere_consultoria/configuration.py
ee_ampere_consultoria/enum_produto.py
ee_ampere_consultoria/request_manager.py
ee_ampere_consultoria/auth/__init__.py
ee_ampere_consultoria/auth/auth_manager.py
ee_ampere_consultoria/produtos/__init__.py
ee_ampere_consultoria/produtos/base_produto.py
ee_ampere_consultoria/produtos/file_viewer/__init__.py
ee_ampere_consultoria/produtos/file_viewer/file_viewer.py
ee_ampere_consultoria/produtos/flux/__init__.py
ee_ampere_consultoria/produtos/flux/body_flux_personalizado.py
ee_ampere_consultoria/produtos/flux/body_flux_personalizado_cenario.py
ee_ampere_consultoria/produtos/flux/body_flux_personalizado_cenario_bloco.py
ee_ampere_consultoria/produtos/flux/body_flux_upload.py
ee_ampere_consultoria/produtos/flux/ena_diaria.py
ee_ampere_consultoria/produtos/flux/enum_dimensoes_agrupamento.py
ee_ampere_consultoria/produtos/flux/flux_automatrico.py
ee_ampere_consultoria/produtos/flux/flux_ec_46.py
ee_ampere_consultoria/produtos/flux/flux_gt.py
ee_ampere_consultoria/produtos/flux/flux_historico.py
ee_ampere_consultoria/produtos/flux/flux_personalizado.py
ee_ampere_consultoria/produtos/flux/flux_upload.py
ee_ampere_consultoria/produtos/meteorologia/__init__.py
ee_ampere_consultoria/produtos/meteorologia/body_chuva_observada.py
ee_ampere_consultoria/produtos/meteorologia/body_comparador.py
ee_ampere_consultoria/produtos/meteorologia/enum_dias_modelos.py
ee_ampere_consultoria/produtos/meteorologia/enum_membros.py
ee_ampere_consultoria/produtos/meteorologia/enum_meteorologia_prazo.py
ee_ampere_consultoria/produtos/meteorologia/enum_modelos.py
ee_ampere_consultoria/produtos/meteorologia/enum_modelos_data_store.py
ee_ampere_consultoria/produtos/meteorologia/enum_niveis_atm.py
ee_ampere_consultoria/produtos/meteorologia/enum_rmvoptions.py
ee_ampere_consultoria/produtos/meteorologia/enum_runtime.py
ee_ampere_consultoria/produtos/meteorologia/enum_tipo_comparacao.py
espaco_exclusivo_package-0.1.34.dist-info/LICENSE
espaco_exclusivo_package-0.1.34.dist-info/METADATA
espaco_exclusivo_package-0.1.34.dist-info/WHEEL
espaco_exclusivo_package-0.1.34.dist-info/top_level.txt
espaco_exclusivo_package-0.1.34.dist-info/RECORD
