Metadata-Version: 2.1
Name: espaco_exclusivo_package
Version: 0.1.34
Summary: Pacote de métodos usados para implementação da API de acesso aos produtos Ampere Consultoria
Home-page: https://gitlab.com/diego.yosiura.ampere/espaco-exclusivo-package.git
Author: Diego Isaac Haruwo Yosiura
Author-email: diego@ampereconsultoria.com.br
Project-URL: Bug Tracker, https://gitlab.com/diego.yosiura.ampere/espaco-exclusivo-package/-/issues
Classifier: Programming Language :: Python :: 3
Classifier: License :: OSI Approved :: MIT License
Classifier: Operating System :: OS Independent
Requires-Python: >=3.6
License-File: LICENSE
Requires-Dist: requests
Requires-Dist: requests-toolbelt
